foxtron_django_settings/__init__.py
foxtron_django_settings/foxtron_django_settings.py
foxtron_django_settings-0.1.2.dist-info/AUTHORS.rst
foxtron_django_settings-0.1.2.dist-info/LICENSE
foxtron_django_settings-0.1.2.dist-info/METADATA
foxtron_django_settings-0.1.2.dist-info/WHEEL
foxtron_django_settings-0.1.2.dist-info/top_level.txt
foxtron_django_settings-0.1.2.dist-info/RECORD
