Metadata-Version: 2.1
Name: foxtron-django-settings
Version: 0.1.2
Summary: Tools used at Foxtron GmbH to simplify the writing of settings.py
Home-page: https://dev.foxtron.ch/foxtron/python/foxtron_django_settings
Author: Samuel Dolt
Author-email: samuel.dolt@foxtron.ch
License: MIT license
Keywords: foxtron_django_settings
Platform: UNKNOWN
Classifier: Development Status :: 2 - Pre-Alpha
Classifier: Intended Audience :: Developers
Classifier: License :: OSI Approved :: MIT License
Classifier: Natural Language :: English
Classifier: Programming Language :: Python :: 3
Classifier: Programming Language :: Python :: 3.5
Classifier: Programming Language :: Python :: 3.6
Classifier: Programming Language :: Python :: 3.7
Classifier: Programming Language :: Python :: 3.8
Requires-Python: >=3.5
